mapped_config/__init__.py
mapped_config/constructor.py
mapped_config/loader.py
mapped_config-2.35.dist-info/DESCRIPTION.rst
mapped_config-2.35.dist-info/METADATA
mapped_config-2.35.dist-info/RECORD
mapped_config-2.35.dist-info/WHEEL
mapped_config-2.35.dist-info/metadata.json
mapped_config-2.35.dist-info/top_level.txt
